{
  "version": "5.4.1",
  "flags": {},
  "shapes": [
    {
      "label": "cell",
      "points": [
        [
          193.999872,
          148.0
        ],
        [
          192.999936,
          148.999936
        ],
        [
          192.0,
          148.999936
        ],
        [
          191.000064,
          150.000128
        ],
        [
          190.000128,
          150.000128
        ],
        [
          188.999936,
          151.000064
        ],
        [
          188.0,
          151.000064
        ],
        [
          184.999936,
          153.999872
        ],
        [
          184.999936,
          161.999872
        ],
        [
          185.999872,
          161.999872
        ],
        [
          187.000064,
          163.000064
        ],
        [
          188.999936,
          163.000064
        ],
        [
          190.000128,
          164.0
        ],
        [
          196.999936,
          164.0
        ],
        [
          198.000128,
          164.999936
        ],
        [
          203.000064,
          164.999936
        ],
        [
          204.0,
          164.0
        ],
        [
          206.000128,
          164.0
        ],
        [
          209.999872,
          160.0
        ],
        [
          209.999872,
          152.999936
        ],
        [
          207.000064,
          150.000128
        ],
        [
          204.0,
          150.000128
        ],
        [
          203.000064,
          148.999936
        ],
        [
          201.999872,
          148.999936
        ],
        [
          200.999936,
          148.0
        ]
      ],
      "group_id": null,
      "description": null,
      "shape_type": "polygon",
      "flags": {},
      "mask": null
    },
    {
      "label": "cell",
      "points": [
        [
          216.999936,
          0.0
        ],
        [
          212.0,
          4.9999872
        ],
        [
          212.0,
          6.0
        ],
        [
          211.000064,
          7.0000128
        ],
        [
          211.000064,
          11.0000128
        ],
        [
          212.0,
          11.0000128
        ],
        [
          214.000128,
          12.9999872
        ],
        [
          215.000064,
          12.9999872
        ],
        [
          216.0,
          14.0
        ],
        [
          224.999936,
          14.0
        ],
        [
          225.999872,
          12.9999872
        ],
        [
          225.999872,
          12.0
        ],
        [
          227.000064,
          11.0000128
        ],
        [
          227.000064,
          6.0
        ],
        [
          225.999872,
          4.9999872
        ],
        [
          225.999872,
          4.0
        ],
        [
          224.999936,
          3.0000128
        ],
        [
          224.999936,
          2.0
        ],
        [
          224.0,
          1.0
        ],
        [
          223.000064,
          1.0
        ],
        [
          222.000128,
          0.0
        ]
      ],
      "group_id": null,
      "description": null,
      "shape_type": "polygon",
      "flags": {},
      "mask": null
    },
    {
      "label": "cell",
      "points": [
        [
          6.0,
          119.000064
        ],
        [
          4.9999872,
          120.0
        ],
        [
          3.0000128,
          120.0
        ],
        [
          3.0000128,
          120.999936
        ],
        [
          2.0,
          121.999872
        ],
        [
          2.0,
          124.0
        ],
        [
          1.0,
          124.999936
        ],
        [
          1.0,
          129.999872
        ],
        [
          2.0,
          131.000064
        ],
        [
          3.0000128,
          131.000064
        ],
        [
          4.0,
          132.0
        ],
        [
          7.0000128,
          132.0
        ],
        [
          8.0,
          131.000064
        ],
        [
          8.9999872,
          131.000064
        ],
        [
          12.0,
          128.0
        ],
        [
          12.0,
          121.999872
        ],
        [
          11.0000128,
          120.999936
        ],
        [
          11.0000128,
          120.0
        ],
        [
          10.0,
          119.000064
        ]
      ],
      "group_id": null,
      "description": null,
      "shape_type": "polygon",
      "flags": {},
      "mask": null
    },
    {
      "label": "cell",
      "points": [
        [
          1.0,
          192.0
        ],
        [
          0.0,
          192.999936
        ],
        [
          0.0,
          204.999936
        ],
        [
          6.0,
          211.000064
        ],
        [
          8.9999872,
          211.000064
        ],
        [
          10.0,
          209.999872
        ],
        [
          12.0,
          209.999872
        ],
        [
          12.9999872,
          208.999936
        ],
        [
          12.9999872,
          200.0
        ],
        [
          11.0000128,
          198.000128
        ],
        [
          11.0000128,
          196.999936
        ],
        [
          8.9999872,
          195.000064
        ],
        [
          8.9999872,
          193.999872
        ],
        [
          7.0000128,
          192.0
        ]
      ],
      "group_id": null,
      "description": null,
      "shape_type": "polygon",
      "flags": {},
      "mask": null
    },
    {
      "label": "cell",
      "points": [
        [
          131.000064,
          92.999936
        ],
        [
          129.999872,
          94.000128
        ],
        [
          127.000064,
          94.000128
        ],
        [
          126.000128,
          95.000064
        ],
        [
          124.999936,
          95.000064
        ],
        [
          124.999936,
          96.0
        ],
        [
          123.000064,
          97.999872
        ],
        [
          123.000064,
          99.000064
        ],
        [
          121.999872,
          100.0
        ],
        [
          121.999872,
          104.999936
        ],
        [
          123.000064,
          105.999872
        ],
        [
          124.0,
          105.999872
        ],
        [
          124.999936,
          107.000064
        ],
        [
          127.000064,
          107.000064
        ],
        [
          128.0,
          108.0
        ],
        [
          131.000064,
          108.0
        ],
        [
          132.0,
          107.000064
        ],
        [
          136.0,
          107.000064
        ],
        [
          136.999936,
          105.999872
        ],
        [
          139.000064,
          105.999872
        ],
        [
          140.999936,
          104.0
        ],
        [
          140.999936,
          96.999936
        ],
        [
          140.0,
          96.0
        ],
        [
          139.000064,
          96.0
        ],
        [
          136.999936,
          94.000128
        ],
        [
          136.0,
          94.000128
        ],
        [
          135.000064,
          92.999936
        ]
      ],
      "group_id": null,
      "description": null,
      "shape_type": "polygon",
      "flags": {},
      "mask": null
    }
  ],
  "imagePath": "b98681c74842c4058bd2f88b06063731c26a90da083b1ef348e0ec734c58752b.png",
  "imageData": null,
  "imageHeight": 256,
  "imageWidth": 256
}